hacapi/__init__.py
hacapi/hac.py
hacapi/misc.py
hacapi/payloads.py
hacapi-0.5.4.1.dist-info/LICENSE
hacapi-0.5.4.1.dist-info/METADATA
hacapi-0.5.4.1.dist-info/WHEEL
hacapi-0.5.4.1.dist-info/RECORD
