Metadata-Version: 2.1
Name: hacapi
Version: 0.5.4.1
Summary: This is a simple API to access the Home Access Center (HAC)
License: MIT
Author: Nazchanel
Author-email: eshaniyer@duck.com
Requires-Python: >=3.6,<4.0
Classifier: License :: OSI Approved :: MIT License
Classifier: Operating System :: OS Independent
Classifier: Programming Language :: Python :: 3
Classifier: Programming Language :: Python :: 3.6
Classifier: Programming Language :: Python :: 3.7
Classifier: Programming Language :: Python :: 3.8
Classifier: Programming Language :: Python :: 3.9
Classifier: Programming Language :: Python :: 3.10
Classifier: Programming Language :: Python :: 3.11
Requires-Dist: beautifulsoup4 (>=4.10.0,<5.0.0)
Requires-Dist: lxml (>=4.6.3,<5.0.0)
Requires-Dist: pandas (>=1.3.3,<2.0.0)
Requires-Dist: requests (>=2.26.0,<3.0.0)
